classic/apriltag.png
classic/apriltag@2x.png
classic/apriltag_frame.png
classic/apriltag_frame@2x.png
classic/neon_event.png
classic/neon_event@2x.png
dark/apriltag.png
dark/apriltag@2x.png
dark/apriltag_frame.png
dark/apriltag_frame@2x.png
dark/neon_event.png
dark/neon_event@2x.png
docs_src/conf.py
docs_src/favicon.png
docs_src/generatePages.py
docs_src/themes/psychopy_plugin/static/Nottingham Supported.png
docs_src/themes/psychopy_plugin/static/Psychopy Plugin Header Large.png
docs_src/themes/psychopy_plugin/static/Psychopy Plugin Header Small.png
light/apriltag.png
light/apriltag@2x.png
light/apriltag_frame.png
light/apriltag_frame@2x.png
light/neon_event.png
light/neon_event@2x.png
psychopy_eyetracker_pupil_labs/__init__.py
psychopy_eyetracker_pupil_labs/classic/apriltag.png
psychopy_eyetracker_pupil_labs/classic/apriltag@2x.png
psychopy_eyetracker_pupil_labs/classic/apriltag_frame.png
psychopy_eyetracker_pupil_labs/classic/apriltag_frame@2x.png
psychopy_eyetracker_pupil_labs/classic/neon_event.png
psychopy_eyetracker_pupil_labs/classic/neon_event@2x.png
psychopy_eyetracker_pupil_labs/dark/apriltag.png
psychopy_eyetracker_pupil_labs/dark/apriltag@2x.png
psychopy_eyetracker_pupil_labs/dark/apriltag_frame.png
psychopy_eyetracker_pupil_labs/dark/apriltag_frame@2x.png
psychopy_eyetracker_pupil_labs/dark/neon_event.png
psychopy_eyetracker_pupil_labs/dark/neon_event@2x.png
psychopy_eyetracker_pupil_labs/light/apriltag.png
psychopy_eyetracker_pupil_labs/light/apriltag@2x.png
psychopy_eyetracker_pupil_labs/light/apriltag_frame.png
psychopy_eyetracker_pupil_labs/light/apriltag_frame@2x.png
psychopy_eyetracker_pupil_labs/light/neon_event.png
psychopy_eyetracker_pupil_labs/light/neon_event@2x.png
psychopy_eyetracker_pupil_labs/pupil_labs/__init__.py
psychopy_eyetracker_pupil_labs/pupil_labs/components.py
psychopy_eyetracker_pupil_labs/pupil_labs/stimuli.py
psychopy_eyetracker_pupil_labs/pupil_labs/neon/__init__.py
psychopy_eyetracker_pupil_labs-0.8.1.dist-info/licenses/LICENSE
psychopy_eyetracker_pupil_labs-0.8.1.dist-info/METADATA
psychopy_eyetracker_pupil_labs-0.8.1.dist-info/WHEEL
psychopy_eyetracker_pupil_labs-0.8.1.dist-info/entry_points.txt
psychopy_eyetracker_pupil_labs-0.8.1.dist-info/top_level.txt
psychopy_eyetracker_pupil_labs-0.8.1.dist-info/RECORD
